pyldb/__init__.py
pyldb/details.py
pyldb/extra/css/board.css
pyldb/extra/images/london_overground.png
pyldb/extra/images/southern.png
pyldb/extra/images/thameslink.png
pyldb/render.py
pyldb/retrieve.py
pyldb/templates/board.html.j2
pyldb/templates/board2.html.j2
pyldb/templates/board3.html.j2
pyldb/templates/debug.html.j2
pyldb-0.7.0.dist-info/METADATA
pyldb-0.7.0.dist-info/WHEEL
pyldb-0.7.0.dist-info/RECORD
