Metadata-Version: 2.1
Name: pyldb
Version: 0.7.0
Summary: Python interface to the Live Departure Boards
License: MIT
Author: Jack Grahl
Author-email: jack.grahl@gmail.com
Requires-Python: >=3.7,<4.0
Classifier: License :: OSI Approved :: MIT License
Classifier: Programming Language :: Python :: 3
Classifier: Programming Language :: Python :: 3.7
Classifier: Programming Language :: Python :: 3.8
Classifier: Programming Language :: Python :: 3.9
Classifier: Programming Language :: Python :: 3.10
Classifier: Programming Language :: Python :: 3.11
Requires-Dist: Jinja2 (>=3.1.2,<4.0.0)
Requires-Dist: suds-py3 (>=1.4.5.0,<2.0.0.0)
